file_storehouse/__init__.py
file_storehouse/_version.py
file_storehouse/extras.py
file_storehouse/py.typed
file_storehouse/type.py
file_storehouse/engine/__init__.py
file_storehouse/engine/base.py
file_storehouse/engine/local_file_system.py
file_storehouse/engine/s3.py
file_storehouse/file_manager/__init__.py
file_storehouse/file_manager/mapping.py
file_storehouse/file_manager/mutable_mapping.py
file_storehouse/key_mapping/__init__.py
file_storehouse/key_mapping/base.py
file_storehouse/key_mapping/numerated_file.py
file_storehouse/key_mapping/numerated_folder.py
file_storehouse/key_mapping/raw.py
file_storehouse/transformation/__init__.py
file_storehouse/transformation/base.py
file_storehouse/transformation/codecs.py
file_storehouse/transformation/json.py
file_storehouse-0.5.1.dist-info/METADATA
file_storehouse-0.5.1.dist-info/WHEEL
file_storehouse-0.5.1.dist-info/licenses/LICENSE
file_storehouse-0.5.1.dist-info/RECORD
