Metadata-Version: 2.4
Name: file-storehouse
Version: 0.5.1
Summary: Manage files in bulk quantity using a friendly dict-like interface
Project-URL: Source, https://github.com/fschuch/file_storehouse
Project-URL: Tracker, https://github.com/fschuch/file_storehouse/issues
Project-URL: Changelog, https://docs.fschuch.com/file_storehouse/references/what-is-new.html
Project-URL: Documentation, https://docs.fschuch.com/file_storehouse/
Author-email: "Felipe N. Schuch" <me@fschuch.com>
License-Expression: MIT
License-File: LICENSE
Classifier: Development Status :: 4 - Beta
Classifier: Intended Audience :: Developers
Classifier: License :: OSI Approved :: MIT License
Classifier: Operating System :: OS Independent
Classifier: Programming Language :: Python
Classifier: Programming Language :: Python :: 3
Classifier: Programming Language :: Python :: 3.9
Classifier: Programming Language :: Python :: 3.10
Classifier: Programming Language :: Python :: 3.11
Classifier: Programming Language :: Python :: 3.12
Classifier: Programming Language :: Python :: 3.13
Requires-Python: >=3.9
Requires-Dist: boto3>=1.24.36
Provides-Extra: docs
Requires-Dist: docutils==0.21.2; extra == 'docs'
Requires-Dist: jupyter-book==1.0.4.post1; extra == 'docs'
Requires-Dist: sphinx-autobuild==2024.10.3; extra == 'docs'
Requires-Dist: sphinx-github-changelog==1.7.1; extra == 'docs'
Requires-Dist: sphinx==7.4.7; extra == 'docs'
Provides-Extra: tests
Requires-Dist: coverage[toml]>=7.5.3; extra == 'tests'
Requires-Dist: hypothesis>=6.52.4; extra == 'tests'
Requires-Dist: pre-commit>=4.2.0; extra == 'tests'
Requires-Dist: pytest-cov>=5.0.0; extra == 'tests'
Requires-Dist: pytest-docker>=3.2.3; extra == 'tests'
Requires-Dist: pytest>=8.2.2; extra == 'tests'
Requires-Dist: pyyaml!=5.4,!=5.4.1,>=5.0.0; extra == 'tests'
Provides-Extra: tests-extra
Requires-Dist: pytest-randomly==3.16.0; extra == 'tests-extra'
Requires-Dist: pytest-rerunfailures==15.1; extra == 'tests-extra'
Requires-Dist: pytest-xdist==3.8.0; extra == 'tests-extra'
